{
  "entity_name": "Gandy",
  "entity_type": "person-mentioned",
  "document_count": 0,
  "summary": "Based on the provided documents, there is no mention of an entity named 'Gandy'. Therefore, it is impossible to provide a summary or any related information about this entity within the context of these documents.",
  "key_connections": [],
  "significance": "Since 'Gandy' is not mentioned in the provided documents, its significance in the JFK context cannot be determined.",
  "document_ids": [
    "124-10326-10103",
    "124-10326-10105",
    "124-90137-10467"
  ]
}