{
  "entity_name": "Proprietary",
  "entity_type": "tag",
  "document_count": 3,
  "summary": "The term \"Proprietary\" appears in the documents primarily in the context of protecting Agency assets and covert operations. In one instance, it refers to a KUBARK proprietary being used as a front to procure a DC-3 aircraft for stranded newsmen in SDOM. The other two instances relate to media inquiries regarding Cuban involvement in the Watergate case and the potential exposure of Agency assets and proprietaries in Miami. The documents highlight the concern for maintaining secrecy and protecting the identities and connections of individuals and organizations associated with the Agency.",
  "key_connections": [
    "KUBARK",
    "AMCORE-2",
    "Cuban exiles",
    "Watergate case",
    "Agency assets"
  ],
  "significance": "In the JFK context, the term \"Proprietary\" signifies the CIA's use of covert assets and organizations to conduct operations, maintain secrecy, and protect its interests. The documents suggest a concern for protecting these assets from exposure, particularly in relation to sensitive matters such as the Watergate case and potential connections to Cuban exiles. While not directly related to the JFK assassination, the documents illustrate the operational environment and the Agency's methods of maintaining deniability and control over its activities.",
  "document_ids": [
    "104-10095-10202",
    "104-10165-10169",
    "104-10062-10046"
  ]
}