{
  "entity_name": "Personnel Action",
  "entity_type": "tag",
  "document_count": 13,
  "summary": "Personnel actions, as reflected in the documents, encompass a range of administrative processes related to CIA employees. These actions include assignments, reassignments, promotions, retirements, resignations, leaves of absence, and terminations. The documents highlight the use of 'Request for Personnel Action' forms to initiate and record these changes. Specific examples include the reassignment of Floryan R. Karty between Mexico City and Bangkok, Anna Tarasoff's leave without pay, Balmes N. Hidalgo Jr.'s retirement, and actions related to individuals like Newton S. Miler, Joseph S. Piccolo, David E. Murphy, Jeremy K. Benadum, and Herman E. Kimsey. These actions are crucial for managing CIA staff and maintaining operational effectiveness. The documents also reveal instances of security concurrence for overseas assignments, such as John F. Rittenhouse's assignment to Mexico City, indicating the importance of security considerations in personnel decisions.",
  "key_connections": [
    "Newton S. Miler",
    "James A. Noel",
    "Joseph S. Piccolo",
    "Floryan R. Karty",
    "Anna Tarasoff",
    "Thomas B. CASASIN (J. Richardson)",
    "Balmes N. Hidalgo Jr.",
    "John F. Rittenhouse",
    "David E. Murphy",
    "James P. O'Connell, Jr.",
    "Jeremy K. Benadum",
    "Herman E. Kimsey",
    "CIA Retirement and Disability System",
    "Mexico City",
    "Bangkok",
    "European Division",
    "Paris Station"
  ],
  "significance": "While 'Personnel Action' itself doesn't directly relate to the JFK assassination, the documents provide insight into the CIA's internal administrative processes and personnel management during the relevant time periods. Understanding these processes can help contextualize the roles and movements of individuals who may have been involved in events related to the assassination. The documents do not explicitly mention the JFK assassination.",
  "document_ids": [
    "104-10224-10007",
    "104-10291-10013",
    "104-10225-10003",
    "104-10222-10043",
    "104-10194-10015",
    "104-10194-10019",
    "104-10194-10022",
    "104-10119-10338",
    "104-10224-10002",
    "104-10194-10014",
    "104-10224-10008",
    "104-10120-10274",
    "104-10224-10004"
  ]
}