{
  "entity_name": "National Reconnaissance Program",
  "entity_type": "tag",
  "document_count": 3,
  "summary": "The National Reconnaissance Program is mentioned in the minutes of the President's Foreign Intelligence Advisory Board (PFIAB) meetings in June, August, and October of 1964. These mentions occur within discussions covering a range of intelligence and national security matters. The program appears to be a topic of interest and importance to the PFIAB, as it is brought up in multiple meetings alongside other critical issues such as intelligence on China, Soviet Bloc threats, audio surveillance, and reconnaissance activities. The specific details of the program's activities or objectives are not elaborated upon in these summaries, but its inclusion in these high-level discussions indicates its significance within the broader intelligence landscape of the time.",
  "key_connections": [
    "President's Foreign Intelligence Advisory Board (PFIAB)",
    "China",
    "Soviet Bloc",
    "Audio Surveillance",
    "Soviet satellite reconnaissance",
    "Defense Intelligence Agency"
  ],
  "significance": "Based on the provided documents, the National Reconnaissance Program's significance in the JFK assassination context is not directly apparent. The documents do not explicitly link the program to the assassination. However, the program's presence in discussions about national security and intelligence matters during the period following the assassination suggests its relevance to the broader geopolitical landscape and intelligence activities of the time.",
  "document_ids": [
    "206-10001-10013",
    "206-10001-10007",
    "206-10001-10000"
  ]
}