{
  "entity_name": "Tad Szulc",
  "entity_type": "tag",
  "document_count": 3,
  "summary": "Tad Szulc was a journalist whose activities and potential connections were of interest to the CIA. Documents indicate the CIA was tracing Szulc's movements and gathering information about him as early as June 1962. He is mentioned in connection with the AMTRUNK operation, a possible political action operation run against the U.S.G./CIA, where his involvement and potential connections to hostile foreign agents were a concern. The documents suggest a focus on Szulc's activities and potential vulnerabilities, possibly related to security concerns or perceived threats to the CIA.",
  "key_connections": [
    "Ignacy Sachs",
    "AMTRUNK Operation",
    "Nestor Antonio MORENO Lopez (AMICE-27)"
  ],
  "significance": "Tad Szulc's significance in the JFK context is related to the CIA's interest in his activities and potential connections, particularly concerning the AMTRUNK operation and possible links to hostile foreign agents. The documents suggest that Szulc was a person of interest to the CIA, possibly due to concerns about his reporting or potential vulnerabilities.",
  "document_ids": [
    "104-10102-10232",
    "104-10102-10233",
    "104-10103-10097"
  ]
}