{
  "entity_name": "Turkish Intelligence",
  "entity_type": "tag",
  "document_count": 3,
  "summary": "Turkish Intelligence, as indicated by the provided documents, was involved in monitoring and reporting on international reactions to President John F. Kennedy's assassination in November and December 1963. Their role appears to be primarily observational, gathering and disseminating information on the sentiments and responses of various countries, including Morocco, Czechoslovakia (Prague), and Finland, to the event and the subsequent transition of power to Lyndon B. Johnson. The reports cover a range of reactions, from expressions of sorrow and condolence to more reserved political assessments. The documents suggest a focus on understanding the global impact and potential implications of Kennedy's death.",
  "key_connections": [
    "Morocco",
    "King of Morocco",
    "Prince Abdullah",
    "Prague",
    "Finland",
    "President John F. Kennedy",
    "Lyndon B. Johnson"
  ],
  "significance": "Turkish Intelligence's significance in the JFK assassination context lies in their role as an information gatherer and reporter on international reactions. While not directly involved in the assassination itself, their reports provide insights into the global impact and immediate aftermath of the event, capturing the diverse responses of different nations and political entities. These reports contribute to a broader understanding of the international context surrounding Kennedy's death and the early days of the Johnson presidency.",
  "document_ids": [
    "144-10001-10348",
    "144-10001-10350",
    "144-10001-10351"
  ]
}