{
  "entity_name": "Fredrick C. Wickham",
  "entity_type": "person-mentioned",
  "document_count": 4,
  "summary": "Based on the provided documents, Fredrick C. Wickham is mentioned in the context of the Assassination Records Review Board's (ARRB) interactions with the CIA regarding JFK assassination records. The documents detail ARRB meetings and the status of CIA responses to ARRB information requests. While the documents mention Wickham, they do not provide specific details about his role or involvement. He is likely a CIA official involved in the process of reviewing and releasing JFK assassination-related documents to the ARRB. The documents span from 1996 to 1998, indicating a timeline of involvement during the ARRB's investigation.",
  "key_connections": [
    "ARRB",
    "CIA",
    "JFK assassination records"
  ],
  "significance": "Fredrick C. Wickham's significance lies in his potential role as a CIA official involved in the declassification and release of JFK assassination records to the ARRB. However, the exact nature and extent of his involvement are not explicitly detailed in the provided documents.",
  "document_ids": [
    "104-10331-10166",
    "104-10332-10000",
    "104-10336-10000",
    "104-10331-10226"
  ]
}