{
  "entity_name": "Dr. Scoville",
  "entity_type": "person-mentioned",
  "document_count": 4,
  "summary": "Based on the provided documents, Dr. Scoville is mentioned in the context of memoranda related to covert operations and reconnaissance activities, particularly concerning Cuba and Southeast Asia, during the period of 1962-1964. The documents primarily focus on discussions and decisions made by the Special Group (Augmented) regarding Operation MONGOOSE, U-2 flights, potential sabotage, and policy decisions related to actions against Cuba. Dr. Scoville's specific role or involvement is not explicitly detailed in the summaries, but the context suggests that he was likely involved in discussions or activities related to these covert operations and reconnaissance efforts. The documents also highlight concerns about maintaining operational secrecy and internal security.",
  "key_connections": [
    "Special Group (Augmented)",
    "Operation MONGOOSE",
    "Cuba",
    "Southeast Asia",
    "DCI (Director of Central Intelligence)"
  ],
  "significance": "Without more specific information, it is difficult to determine Dr. Scoville's direct significance to the JFK assassination. The documents suggest involvement in covert operations and reconnaissance, particularly related to Cuba, which was a significant area of concern during the Kennedy administration. Further research would be needed to establish any direct connection to events surrounding the assassination.",
  "document_ids": [
    "206-10001-10015",
    "104-10306-10003",
    "104-10306-10024",
    "104-10306-10011"
  ]
}