{
  "entity_name": "David Ferrie",
  "entity_type": "person-mentioned",
  "document_count": 9,
  "summary": "David Ferrie was associated with Lee Harvey Oswald and the Civil Air Patrol Cadets (CAPC) in New Orleans. He is mentioned in connection to possible illegal activities and suspicious conversations. He is also linked to anti-Castro Cuban groups and individuals. Documents suggest investigations into his activities and connections to the JFK assassination. Phillip Geraci had limited association with David Ferrie. Jimmy Johnson made a phone call regarding Ferrie and the Smith case.",
  "key_connections": [
    "Lee Harvey Oswald",
    "Jimmy Johnson",
    "Phillip Geraci",
    "Carlos Bringuier",
    "Anti-Castro Cuban groups",
    "Civil Air Patrol Cadets (CAPC)"
  ],
  "significance": "David Ferrie's significance in the JFK assassination context stems from his connections to Lee Harvey Oswald and his alleged involvement with anti-Castro activities. His name appears in investigations and interviews related to the assassination, raising questions about his potential role or knowledge of the events.",
  "document_ids": [
    "180-10145-10269",
    "180-10076-10105",
    "180-10107-10006",
    "135-10001-10276",
    "180-10106-10008",
    "180-10145-10308",
    "178-10002-10091",
    "180-10145-10295",
    "104-10079-10016"
  ]
}