{
  "entity_name": "Ronald Reagan",
  "entity_type": "person-mentioned",
  "document_count": 3,
  "summary": "Based on the provided documents, Ronald Reagan is mentioned in the context of CIA activities and investigations into potential domestic operations. The documents consist of memoranda and testimony related to CIA's counter-intelligence staff, handling of information related to Americans, and activities of the Office of Security. However, the documents do not provide specific details about Ronald Reagan's direct involvement or role in any of these activities. His presence is noted as a person mentioned within the broader scope of CIA-related inquiries during the mid-1970s.",
  "key_connections": [],
  "significance": "The provided documents do not establish any direct significance of Ronald Reagan in the JFK assassination context. His mention appears incidental to investigations into CIA activities during the 1970s.",
  "document_ids": [
    "178-10004-10396",
    "135-10001-10287",
    "157-10011-10078"
  ]
}