{
  "entity_name": "National Security Files",
  "entity_type": "tag",
  "document_count": 3,
  "summary": "The documents tagged with \"National Security Files\" cover a range of sensitive topics during the Kennedy administration, including covert operations and foreign policy decisions. These files touch upon Cuban financing of subversive activities in Latin America, U.S. policy regarding a potential coup in South Vietnam, and the overall status of Southeast Asia. The documents highlight the administration's focus on managing international crises and engaging in clandestine activities to further U.S. interests during the Cold War era. The files also reveal the involvement of key figures like McGeorge Bundy and the U.S. Ambassador to Saigon, indicating high-level decision-making and strategic planning.",
  "key_connections": [
    "Cuba",
    "Latin America",
    "South Vietnam",
    "McGeorge Bundy",
    "Ambassador Lodge",
    "Southeast Asia",
    "Task Force Southeast Asia",
    "Viet-Nam",
    "Thailand",
    "Laos",
    "Burma",
    "Cambodia"
  ],
  "significance": "While the provided documents do not directly mention the JFK assassination, they offer insight into the political climate and covert operations authorized during Kennedy's presidency. The focus on Cuba, Vietnam, and other Cold War hotspots provides context for understanding the complex geopolitical landscape in which the assassination occurred. The documents also reveal the administration's willingness to engage in clandestine activities, which could be relevant to understanding potential motives or actors involved in the assassination.",
  "document_ids": [
    "176-10036-10065",
    "176-10036-10173",
    "176-10036-10179"
  ]
}