{
  "entity_name": "Bombings",
  "entity_type": "tag",
  "document_count": 4,
  "summary": "The documents reference bombings in the context of anti-Castro activities and investigations into Cuban exile groups. Bombings are mentioned in connection with Orlando Bosch Avila's anti-Cuba operations, activities of the Directorio Revolucionario Estudiantil (DRE) in Havana, and investigations into Cuban Power and MIRR related to bombings in Miami. Additionally, a fugitive named Albert Larrain Maestre is alleged to have admitted involvement in bombings with Rosenthal. The documents span from 1962 to 1978, indicating a sustained period of such activities. A notable pattern is the association of bombings with Cuban exile groups and their opposition to the Cuban government.",
  "key_connections": [
    "Orlando Bosch Avila",
    "Directorio Revolucionario Estudiantil (DRE)",
    "Cuban Power",
    "MIRR",
    "Albert Larrain Maestre",
    "Rosenthal",
    "Anti-Cuba operations"
  ],
  "significance": "While the documents do not directly link bombings to the JFK assassination, they highlight the volatile environment and activities of anti-Castro groups in the years leading up to and following the assassination. The involvement of individuals and groups in bombings suggests a willingness to use violence, which could be relevant in understanding the broader context of potential actors and motives related to the assassination.",
  "document_ids": [
    "180-10145-10301",
    "104-10171-10018",
    "124-10213-10310",
    "104-10178-10096"
  ]
}