{
  "entity_name": "Communist Influence",
  "entity_type": "tag",
  "document_count": 7,
  "summary": "The documents reflect investigations, primarily by the FBI, into potential communist influence within the Civil Rights Movement, specifically concerning Martin Luther King Jr., the Southern Christian Leadership Conference (SCLC), and Stanley Levison. The investigations involved electronic surveillance and aimed to uncover connections between these individuals and organizations and communist elements. One document outlines a proposal to recruit an individual to gather intelligence on Communist, Castroist, and radical influences within the civil rights movement, focusing on foreign attempts to exploit the situation. The timeline of these investigations appears to center around the 1960s and 1970s, with multiple documents referencing testimony given in 1975 regarding earlier investigations. A notable pattern across the documents is the focus on alleged communist connections as a point of investigation into civil rights leaders and organizations.",
  "key_connections": [
    "Martin Luther King Jr.",
    "Southern Christian Leadership Conference (SCLC)",
    "Stanley Levison",
    "FBI",
    "Senate Select Committee (SSC)",
    "Carlene Hatcher Polite",
    "SNCC"
  ],
  "significance": "In the context of these documents, the significance of 'Communist Influence' lies in its use as a justification for investigations and surveillance of civil rights leaders and organizations. The documents suggest an effort to link the Civil Rights Movement to communist elements, potentially to discredit or undermine the movement. The documents do not directly link Communist Influence to the JFK assassination, but the investigations and surveillance activities described could be relevant to understanding the broader political climate and intelligence operations of the time.",
  "document_ids": [
    "124-10276-10482_multirif",
    "104-10072-10315",
    "124-10273-10014_multirif",
    "124-10274-10357_multirif",
    "124-10273-10008_multirif",
    "124-10276-10483_multirif",
    "124-10273-10018_multirif"
  ]
}