{
  "entity_name": "Personnel Records",
  "entity_type": "tag",
  "document_count": 67,
  "summary": "The documents categorized under \"Personnel Records\" primarily consist of payroll authorizations, memoranda, and related correspondence concerning individuals employed by the House Select Committee on Assassinations (HSCA) and the CIA. These records detail employment terms, salary adjustments, leave records, and sometimes include resumes and certifications regarding relationships with members of Congress. A recurring theme is the redaction or postponement of Social Security numbers to protect personal privacy, as determined by the Assassination Records Review Board. The documents span from the 1960s to the late 1970s, with some notifications extending into the 1990s regarding the release status of these records. The records also include personnel actions such as promotions, reassignments, and retirements within the CIA, as well as background checks and security reviews.",
  "key_connections": [
    "House Select Committee on Assassinations (HSCA)",
    "CIA",
    "Assassination Records Review Board",
    "Martin Luther King Task Force",
    "Thomas Wayne Sacco",
    "Louis Parisi",
    "James S. Woods",
    "Kenneth S. McHargh",
    "Phoebe Curtis Orr",
    "Vivian L. McPherson",
    "James B. Wilcott, Jr.",
    "Paul T. Golden",
    "Brenda L. Welburn",
    "Antoinette M. Roberts",
    "Melvin Kreidman",
    "Surell Brady",
    "Michael Ewing",
    "Barbara Jean Robinson",
    "Dominick K. Giangrasso",
    "Ernestine G. Johnson",
    "Guy Vitale",
    "Dawne C. Miller",
    "Elizabeth M. Norris",
    "Sheila Jackson Lee",
    "Beverly Ann Smith",
    "Robin David Lindley",
    "Beth Anne Lichtenfels",
    "Cecelia T. Morton",
    "Paul A. Zevnik",
    "Nancy S. Jenkins",
    "Rita L. Morton",
    "Johanna Lynn Smith",
    "Sari Mordana",
    "Edwin J. Lopez",
    "E. Howard Hunt, Jr.",
    "Charles Michael Berk",
    "William M. Kent",
    "Belford L. Lawson III",
    "William A. Webb",
    "Robert K. Tanenbaum",
    "Lucien Conein",
    "Nancy P. Schultz",
    "Rebecca Wheeler Martin",
    "Billie Gay Larson",
    "Oliver J. Champion",
    "Kevin Sean Doyle",
    "Dan L. Hardway",
    "Leslie H. Wizelman",
    "Francis J. Kelly",
    "Cornish F. Hitchcock",
    "Merete Muff Rosen",
    "Judith R. Burford",
    "Leodis C. Matthews",
    "Elizabeth Kilker",
    "Jan Richard Schlichtmann"
  ],
  "significance": "In the context of the JFK assassination, personnel records are significant for identifying individuals involved in the investigation, their roles, and potential connections to other relevant organizations or events. They provide insights into the staffing and operations of the HSCA, which was tasked with reinvestigating the assassination. The records also shed light on the CIA's involvement and the individuals associated with the agency who may have had knowledge or played a role in the events surrounding the assassination. The redaction of sensitive information, such as Social Security numbers, highlights the ongoing efforts to balance transparency with the protection of personal privacy.",
  "document_ids": [
    "180-10147-10259",
    "180-10060-10498",
    "104-10291-10004",
    "104-10120-10666",
    "180-10060-10482",
    "104-10146-10198",
    "180-10060-10495",
    "180-10060-10483",
    "104-10195-10003",
    "180-10068-10359",
    "180-10070-10170",
    "104-10147-10216",
    "180-10070-10146",
    "180-10060-10460",
    "180-10068-10314",
    "104-10133-10207",
    "180-10068-10343",
    "180-10147-10258",
    "180-10068-10355",
    "180-10060-10451",
    "180-10060-10447",
    "104-10194-10017",
    "180-10060-10484",
    "180-10060-10492",
    "180-10060-10467",
    "180-10070-10157",
    "194-10004-10371",
    "180-10060-10471",
    "104-10061-10292",
    "180-10060-10470",
    "180-10060-10489",
    "180-10070-10176",
    "180-10060-10450",
    "180-10060-10490",
    "180-10070-10159",
    "180-10060-10486",
    "194-10006-10314",
    "180-10060-10473",
    "194-10004-10373",
    "104-10194-10023",
    "180-10068-10306",
    "104-10128-10249",
    "104-10291-10021",
    "180-10060-10464",
    "180-10060-10472",
    "104-10406-10139",
    "180-10147-10266",
    "104-10221-10003",
    "180-10070-10162",
    "104-10222-10041",
    "180-10070-10158",
    "180-10070-10153",
    "180-10060-10475",
    "180-10060-10463",
    "180-10125-10172",
    "180-10068-10321",
    "180-10068-10337",
    "180-10060-10438",
    "180-10070-10173",
    "180-10060-10455",
    "180-10060-10442",
    "104-10111-10104",
    "180-10070-10148",
    "180-10068-10320",
    "180-10060-10478",
    "180-10060-10458",
    "180-10070-10152"
  ]
}