{
  "entity_name": "Lumumba",
  "entity_type": "tag",
  "document_count": 3,
  "summary": "Patrice Lumumba was a Congolese politician and the first Prime Minister of the Democratic Republic of the Congo. The documents indicate that the CIA was involved in assassination plots against him. These plots were discussed in the context of CIA activities, including those against Fidel Castro and discussions about 'Executive Action'. The documents reference discussions and testimony regarding these plots, including the involvement of individuals like DCI William Colby and Gordon Gray. The timeline of involvement is not explicitly detailed in these documents, but they suggest that the plots were considered during the Eisenhower administration and investigated in the 1970s. A notable pattern across the documents is the consistent mention of Lumumba alongside Castro as targets of potential CIA assassination attempts.",
  "key_connections": [
    "Fidel Castro",
    "CIA",
    "William Colby",
    "Gordon Gray",
    "Dwight D. Eisenhower",
    "Trujillo"
  ],
  "significance": "In the context of the JFK assassination, the references to Lumumba highlight the CIA's involvement in assassination plots against foreign leaders. This is relevant because it provides insight into the agency's operational methods and potential motivations, which are often scrutinized in discussions surrounding the JFK assassination. The documents suggest a pattern of CIA involvement in covert actions, including assassination attempts, which could be relevant when examining the agency's role in other events, including the assassination of JFK.",
  "document_ids": [
    "157-10011-10006",
    "157-10011-10024",
    "157-10014-10100"
  ]
}